dnnet/__init__.py
dnnet/__version__.py
dnnet/config.py
dnnet/exception.py
dnnet/ext_mathlibs.py
dnnet/neuralnet.py
dnnet/layers/__init__.py
dnnet/layers/activation.py
dnnet/layers/affine.py
dnnet/layers/batch_norm.py
dnnet/layers/convolution.py
dnnet/layers/dropout.py
dnnet/layers/layer.py
dnnet/layers/pooling.py
dnnet/training/__init__.py
dnnet/training/back_propagation.py
dnnet/training/learning_curve.py
dnnet/training/loss_function.py
dnnet/training/optimizer.py
dnnet/training/weight_initialization.py
dnnet/utils/__init__.py
dnnet/utils/cnn_utils.py
dnnet/utils/nn_utils.py
dnnet/utils/numcupy.py
dnnet-0.10.1.dist-info/LICENSE
dnnet-0.10.1.dist-info/METADATA
dnnet-0.10.1.dist-info/WHEEL
dnnet-0.10.1.dist-info/top_level.txt
dnnet-0.10.1.dist-info/RECORD
