Metadata-Version: 2.1
Name: dnnet
Version: 0.10.1
Summary: Deep Neural Network.
Home-page: https://github.com/daichi-yoshikawa/dnnet
Author: Daichi Yoshikawa
Author-email: daichi.yoshikawa@gmail.com
License: BSD-3-Clause
Platform: UNKNOWN
Classifier: Development Status :: 4 - Beta
Classifier: Intended Audience :: Science/Research
Classifier: License :: OSI Approved :: BSD License
Classifier: Natural Language :: English
Classifier: Programming Language :: Python
Classifier: Programming Language :: Python :: 3.4
Classifier: Programming Language :: Python :: 3.5
Classifier: Programming Language :: Python :: 3.6
Classifier: Programming Language :: Python :: 3.7
Classifier: Programming Language :: Python :: 3.8
Classifier: Topic :: Scientific/Engineering :: Artificial Intelligence
Requires-Python: >=3.4
Requires-Dist: numpy (>=1.12.0)
